MANIFEST.in
README.md
setup.py
kdn/__init__.py
kdn/api/__init__.py
kdn/api/comm.py
kdn/api/kdn.py
kdn/api/logistic.py
kdn/api/order.py
kdn/api/query.py
kdn/api/service.py
kdn/api/utils.py
kdn/data/direct.csv
kdn/data/eorder.csv
kdn/data/express.csv
kdn/data/exptype.csv
kdn/data/kdn.csv
kdn/data/month.csv
kdn/data/offline.csv
kdn/data/preorder.csv
kdn/data/templates.csv
kdn/data/trans.csv
kdn/tests/__init__.py
kdn/tests/test_comm.py
kdn/tests/test_logistic.py
kdn/tests/test_onroad.py
kdn/tests/test_order.py
kdn/tests/test_query.py
kdn/tests/test_service.py
kdn_sdk.egg-info/PKG-INFO
kdn_sdk.egg-info/SOURCES.txt
kdn_sdk.egg-info/dependency_links.txt
kdn_sdk.egg-info/requires.txt
kdn_sdk.egg-info/top_level.txt
kdn_sdk.egg-info/zip-safe